{"examenes": [{"Orina": 1, "Glucosa": 1, "Colesterol": 1, "Trigiceridos": 1, "Bilirrubina": 1, "Fecha": "2020-12-12"}, {"orina": "123", "glucosa": 1, "colesterol": 1, "triglicerido": 1, "bilirrubina": 1, "fecha": "2020-12-01"}, {"orina": "133", "glucosa": 1, "colesterol": 1, "triglicerido": 1, "bilirrubina": 1, "fecha": "2020-12-02"}, {"orina": "333", "glucosa": 1, "colesterol": 1, "triglicerido": 1, "bilirrubina": 2, "fecha": "2020-12-02"}, {"orina": "333", "glucosa": 1, "colesterol": 1, "triglicerido": 1, "bilirrubina": 2, "fecha": "2020-12-02"}, {"orina": "333", "glucosa": 1, "colesterol": 1, "triglicerido": 1, "bilirrubina": 2, "fecha": "2020-12-02"}, {"orina": "222", "glucosa": 2, "colesterol": 2, "triglicerido": 2, "bilirrubina": 2, "fecha": "2020-12-01"}, {"orina": "555", "glucosa": 5, "colesterol": 5, "triglicerido": 5, "bilirrubina": 5, "fecha": "2020-12-01"}]}